{
  "year": 2017,
  "season": "winter",
  "entries": [
    {
      "mikan_id": "713",
      "bgmtv_id": 155778,
      "title_chinese": "双星之阴阳师",
      "title_japanese": "双星の陰陽師",
      "air_week": 3,
      "poster_url": "https://mikanani.me/images/Bangumi/201604/8abac023.jpg",
      "year": 2016,
      "platform": "tv",
      "total_episodes": 50,
      "air_date": "2016-04-06"
    },
    {
      "mikan_id": "712",
      "bgmtv_id": 170044,
      "title_chinese": "战斗之魂 双重驱动",
      "title_japanese": "バトルスピリッツ ダブルドライブ",
      "air_week": 3,
      "poster_url": "https://mikanani.me/images/Bangumi/201604/4c1a909c.jpg",
      "year": 2016,
      "platform": "tv",
      "total_episodes": 53,
      "air_date": "2016-04-06"
    },
    {
      "mikan_id": "575",
      "bgmtv_id": 137894,
      "title_chinese": "见习神明 秘密的心灵 第一部",
      "title_japanese": "かみさまみならい ヒミツのここたま 第1シリーズ",
      "air_week": 4,
      "poster_url": "https://mikanani.me/images/Bangumi/201510/1ae6a190.jpg",
      "year": 2015,
      "platform": "tv",
      "total_episodes": 76,
      "air_date": "2015-10-01"
    },
    {
      "mikan_id": "1189",
      "bgmtv_id": 185291,
      "title_chinese": "Piacevole～我的意大利料理～",
      "title_japanese": "ピアシェ～私のイタリアン～",
      "air_week": 3,
      "poster_url": "https://mikanani.me/images/Bangumi/201701/fc366924.jpg",
      "year": 2017,
      "platform": "tv",
      "total_episodes": 12,
      "air_date": "2017-01-11"
    },
    {
      "mikan_id": "746",
      "bgmtv_id": 168468,
      "title_chinese": "猫猫日本史",
      "title_japanese": "ねこねこ日本史",
      "air_week": 3,
      "poster_url": "https://mikanani.me/images/Bangumi/201604/c4417d78.jpg",
      "year": 2016,
      "platform": "tv",
      "total_episodes": 32,
      "air_date": "2016-04-06"
    },
    {
      "mikan_id": "1164",
      "bgmtv_id": 174043,
      "title_chinese": "为美好的世界献上祝福！ 第二季",
      "title_japanese": "この素晴らしい世界に祝福を！2",
      "air_week": 3,
      "poster_url": "https://mikanani.me/images/Bangumi/201701/79a13d24.jpg",
      "year": 2017,
      "platform": "tv",
      "total_episodes": 10,
      "air_date": "2017-01-11"
    },
    {
      "mikan_id": "1216",
      "bgmtv_id": 198714,
      "title_chinese": "黑白来看守所 第二季",
      "title_japanese": "ナンバカ 第2期",
      "air_week": 3,
      "poster_url": "https://mikanani.me/images/Bangumi/201701/43930b35.jpg",
      "year": 2017,
      "platform": "tv",
      "total_episodes": 13,
      "air_date": "2017-01-04"
    },
    {
      "mikan_id": "1160",
      "bgmtv_id": 192794,
      "title_chinese": "秋叶原之旅",
      "title_japanese": "AKIBA'S TRIP -THE ANIMATION-",
      "air_week": 3,
      "poster_url": "https://mikanani.me/images/Bangumi/201701/a8fc7b39.jpg",
      "year": 2017,
      "platform": "tv",
      "total_episodes": 13,
      "air_date": "2017-01-04"
    },
    {
      "mikan_id": "1191",
      "bgmtv_id": 129805,
      "title_chinese": "混沌子",
      "title_japanese": "CHAOS;CHILD",
      "air_week": 3,
      "poster_url": "https://mikanani.me/images/Bangumi/201701/ca6ba01b.jpg",
      "year": 2017,
      "platform": "tv",
      "total_episodes": 13,
      "air_date": "2017-01-11"
    },
    {
      "mikan_id": "1168",
      "bgmtv_id": 179949,
      "title_chinese": "小林家的龙女仆",
      "title_japanese": "小林さんちのメイドラゴン",
      "air_week": 3,
      "poster_url": "https://mikanani.me/images/Bangumi/201701/c04f8212.jpg",
      "year": 2017,
      "platform": "tv",
      "total_episodes": 21,
      "air_date": "2017-01-11"
    },
    {
      "mikan_id": "1190",
      "bgmtv_id": 198395,
      "title_chinese": "One Room",
      "title_japanese": "One Room",
      "air_week": 3,
      "poster_url": "https://mikanani.me/images/Bangumi/201701/bf501691.jpg",
      "year": 2017,
      "platform": "tv",
      "total_episodes": 13,
      "air_date": "2017-01-11"
    },
    {
      "mikan_id": "229",
      "bgmtv_id": 2782,
      "title_chinese": "火影忍者疾风传",
      "title_japanese": "NARUTO -ナルト- 疾風伝",
      "air_week": 4,
      "poster_url": "https://mikanani.me/images/Bangumi/201310/ec23bffb.jpg",
      "year": 2007,
      "platform": "tv",
      "total_episodes": 500,
      "air_date": "2007-02-15"
    },
    {
      "mikan_id": "863",
      "bgmtv_id": 146172,
      "title_chinese": "ALL OUT!!",
      "title_japanese": "ALL OUT!!",
      "air_week": 4,
      "poster_url": "https://mikanani.me/images/Bangumi/201610/39dcb413.jpg",
      "year": 2016,
      "platform": "tv",
      "total_episodes": 25,
      "air_date": "2016-10-06"
    },
    {
      "mikan_id": "718",
      "bgmtv_id": 169274,
      "title_chinese": "偶像活动Stars",
      "title_japanese": "アイカツスターズ!",
      "air_week": 4,
      "poster_url": "https://mikanani.me/images/Bangumi/201604/8f9b0523.jpg",
      "year": 2016,
      "platform": "tv",
      "total_episodes": 50,
      "air_date": "2016-04-07"
    },
    {
      "mikan_id": "1194",
      "bgmtv_id": 174143,
      "title_chinese": "人渣的本愿",
      "title_japanese": "クズの本懐",
      "air_week": 4,
      "poster_url": "https://mikanani.me/images/Bangumi/201701/757ae9f9.jpg",
      "year": 2017,
      "platform": "tv",
      "total_episodes": 12,
      "air_date": "2017-01-12"
    },
    {
      "mikan_id": "1172",
      "bgmtv_id": 195229,
      "title_chinese": "清恋",
      "title_japanese": "セイレン",
      "air_week": 4,
      "poster_url": "https://mikanani.me/images/Bangumi/201701/9a9c367e.jpg",
      "year": 2017,
      "platform": "tv",
      "total_episodes": 12,
      "air_date": "2017-01-05"
    },
    {
      "mikan_id": "1158",
      "bgmtv_id": 185762,
      "title_chinese": "政宗君的复仇",
      "title_japanese": "政宗くんのリベンジ",
      "air_week": 4,
      "poster_url": "https://mikanani.me/images/Bangumi/201701/cc7b1526.jpg",
      "year": 2017,
      "platform": "tv",
      "total_episodes": 12,
      "air_date": "2017-01-05"
    },
    {
      "mikan_id": "681",
      "bgmtv_id": 18692,
      "title_chinese": "哆啦A梦",
      "title_japanese": "ドラえもん",
      "air_week": 5,
      "poster_url": "https://mikanani.me/images/Bangumi/200504/1df90634.jpg",
      "year": 2005,
      "platform": "tv",
      "total_episodes": 913,
      "air_date": "2005-04-15"
    },
    {
      "mikan_id": "1162",
      "bgmtv_id": 196023,
      "title_chinese": "Schoolgirl Strikers",
      "title_japanese": "スクールガールストライカーズ Animation Channel",
      "air_week": 5,
      "poster_url": "https://mikanani.me/images/Bangumi/201701/4cfe2681.jpg",
      "year": 2017,
      "platform": "tv",
      "total_episodes": 13,
      "air_date": "2017-01-06"
    },
    {
      "mikan_id": "1169",
      "bgmtv_id": 173303,
      "title_chinese": "Urara迷路帖",
      "title_japanese": "うらら迷路帖",
      "air_week": 4,
      "poster_url": "https://mikanani.me/images/Bangumi/201701/90b93a8a.jpg",
      "year": 2017,
      "platform": "tv",
      "total_episodes": 12,
      "air_date": "2017-01-05"
    },
    {
      "mikan_id": "1192",
      "bgmtv_id": 169153,
      "title_chinese": "MARGINAL#4 从KISS开始创造Big Bang",
      "title_japanese": "MARGINAL#4 KISSから創造るBig Bang",
      "air_week": 4,
      "poster_url": "https://mikanani.me/images/Bangumi/201701/380bfe29.jpg",
      "year": 2017,
      "platform": "tv",
      "total_episodes": 12,
      "air_date": "2017-01-12"
    },
    {
      "mikan_id": "1193",
      "bgmtv_id": 184727,
      "title_chinese": "超级恋人 第二季",
      "title_japanese": "SUPER LOVERS 2",
      "air_week": 4,
      "poster_url": "https://mikanani.me/images/Bangumi/201701/85d14102.jpg",
      "year": 2017,
      "platform": "tv",
      "total_episodes": 10,
      "air_date": "2017-01-12"
    },
    {
      "mikan_id": "1175",
      "bgmtv_id": 143205,
      "title_chinese": "南镰仓高校女子自行车社",
      "title_japanese": "南鎌倉高校女子自転車部",
      "air_week": 5,
      "poster_url": "https://mikanani.me/images/Bangumi/201701/fdef4c86.jpg",
      "year": 2017,
      "platform": "tv",
      "total_episodes": 13,
      "air_date": "2017-01-06"
    },
    {
      "mikan_id": "1174",
      "bgmtv_id": 188412,
      "title_chinese": "风夏",
      "title_japanese": "風夏",
      "air_week": 5,
      "poster_url": "https://mikanani.me/images/Bangumi/201701/b9b9f7a0.jpg",
      "year": 2017,
      "platform": "tv",
      "total_episodes": 12,
      "air_date": "2017-01-06"
    },
    {
      "mikan_id": "247",
      "bgmtv_id": 83124,
      "title_chinese": "妖怪手表",
      "title_japanese": "妖怪ウォッチ",
      "air_week": 5,
      "poster_url": "https://mikanani.me/images/Bangumi/201401/89e3818d.jpg",
      "year": 2014,
      "platform": "tv",
      "total_episodes": 215,
      "air_date": "2014-01-08"
    },
    {
      "mikan_id": "826",
      "bgmtv_id": 171366,
      "title_chinese": "虎面人W",
      "title_japanese": "タイガーマスクW",
      "air_week": 6,
      "poster_url": "https://mikanani.me/images/Bangumi/201610/85bb2e2a.jpg",
      "year": 2016,
      "platform": "tv",
      "total_episodes": 38,
      "air_date": "2016-10-01"
    },
    {
      "mikan_id": "1176",
      "bgmtv_id": 186034,
      "title_chinese": "青之驱魔师 京都不净王篇",
      "title_japanese": "青の祓魔師 京都不浄王篇",
      "air_week": 5,
      "poster_url": "https://mikanani.me/images/Bangumi/201701/d02a9da0.jpg",
      "year": 2017,
      "platform": "tv",
      "total_episodes": 12,
      "air_date": "2017-01-06"
    },
    {
      "mikan_id": "1215",
      "bgmtv_id": 170762,
      "title_chinese": "暗杀教室 第二季 课外授课篇",
      "title_japanese": "暗殺教室 第2期 課外授業編",
      "air_week": 5,
      "poster_url": "https://mikanani.me/images/Bangumi/201701/3bd3e855.jpg",
      "year": 2016,
      "platform": "tv",
      "total_episodes": 8,
      "air_date": "2016-03-11"
    },
    {
      "mikan_id": "1214",
      "bgmtv_id": 122772,
      "title_chinese": "六心公主",
      "title_japanese": "シックスハートプリンセス",
      "air_week": 5,
      "poster_url": "https://mikanani.me/images/Bangumi/201612/7dcce616.jpg",
      "year": 2016,
      "platform": "tv",
      "total_episodes": 11,
      "air_date": "2016-12-30"
    },
    {
      "mikan_id": "1178",
      "bgmtv_id": 175432,
      "title_chinese": "从前有座灵剑山 第二季",
      "title_japanese": "从前有座灵剑山 第二季",
      "air_week": 5,
      "poster_url": "https://mikanani.me/images/Bangumi/201701/619ee01d.jpg",
      "year": 2017,
      "platform": "tv",
      "total_episodes": 12,
      "air_date": "2017-01-06"
    },
    {
      "mikan_id": "1177",
      "bgmtv_id": 176615,
      "title_chinese": "昭和元禄落语心中 -助六再临篇-",
      "title_japanese": "昭和元禄落語心中 -助六再び篇-",
      "air_week": 5,
      "poster_url": "https://mikanani.me/images/Bangumi/201701/73f4f832.jpg",
      "year": 2017,
      "platform": "tv",
      "total_episodes": 12,
      "air_date": "2017-01-06"
    },
    {
      "mikan_id": "818",
      "bgmtv_id": 175529,
      "title_chinese": "时间飞船24",
      "title_japanese": "タイムボカン24",
      "air_week": 6,
      "poster_url": "https://mikanani.me/images/Bangumi/201610/2d3f9b1e.jpg",
      "year": 2016,
      "platform": "tv",
      "total_episodes": 24,
      "air_date": "2016-10-01"
    },
    {
      "mikan_id": "817",
      "bgmtv_id": 183216,
      "title_chinese": "数码宝贝宇宙 应用怪兽",
      "title_japanese": "デジモンユニバース アプリモンスターズ",
      "air_week": 6,
      "poster_url": "https://mikanani.me/images/Bangumi/201610/884e7cf9.jpg",
      "year": 2016,
      "platform": "tv",
      "total_episodes": 52,
      "air_date": "2016-10-01"
    },
    {
      "mikan_id": "1173",
      "bgmtv_id": 167655,
      "title_chinese": "幼女战记",
      "title_japanese": "幼女戦記",
      "air_week": 5,
      "poster_url": "https://mikanani.me/images/Bangumi/201701/ca7c79d9.jpg",
      "year": 2017,
      "platform": "tv",
      "total_episodes": 13,
      "air_date": "2017-01-06"
    },
    {
      "mikan_id": "1166",
      "bgmtv_id": 186515,
      "title_chinese": "BanG Dream!",
      "title_japanese": "BanG Dream!",
      "air_week": 6,
      "poster_url": "https://mikanani.me/images/Bangumi/201701/edd49cda.jpg",
      "year": 2017,
      "platform": "tv",
      "total_episodes": 14,
      "air_date": "2017-01-21"
    },
    {
      "mikan_id": "872",
      "bgmtv_id": 139137,
      "title_chinese": "克拉斯卡劳埃德",
      "title_japanese": "クラシカロイド",
      "air_week": 6,
      "poster_url": "https://mikanani.me/images/Bangumi/201610/ea31470b.jpg",
      "year": 2016,
      "platform": "tv",
      "total_episodes": 25,
      "air_date": "2016-10-08"
    },
    {
      "mikan_id": "874",
      "bgmtv_id": 147068,
      "title_chinese": "3月的狮子",
      "title_japanese": "3月のライオン",
      "air_week": 6,
      "poster_url": "https://mikanani.me/images/Bangumi/201610/03d48bd6.jpg",
      "year": 2016,
      "platform": "tv",
      "total_episodes": 33,
      "air_date": "2016-10-08"
    },
    {
      "mikan_id": "873",
      "bgmtv_id": 131800,
      "title_chinese": "长骑美眉",
      "title_japanese": "ろんぐらいだぁす！",
      "air_week": 6,
      "poster_url": "https://mikanani.me/images/Bangumi/201610/9c2ec065.jpg",
      "year": 2016,
      "platform": "tv",
      "total_episodes": 13,
      "air_date": "2016-10-08"
    },
    {
      "mikan_id": "1161",
      "bgmtv_id": 191956,
      "title_chinese": "亚人酱有话要说",
      "title_japanese": "亜人ちゃんは語りたい",
      "air_week": 6,
      "poster_url": "https://mikanani.me/images/Bangumi/201701/e320d38b.jpg",
      "year": 2017,
      "platform": "tv",
      "total_episodes": 13,
      "air_date": "2017-01-07"
    },
    {
      "mikan_id": "1179",
      "bgmtv_id": 125900,
      "title_chinese": "锁链战记～赫克瑟塔斯之光～",
      "title_japanese": "チェインクロニクル ～ヘクセイタスの閃～",
      "air_week": 6,
      "poster_url": "https://mikanani.me/images/Bangumi/201701/532bc4eb.jpg",
      "year": 2017,
      "platform": "tv",
      "total_episodes": 12,
      "air_date": "2017-01-07"
    },
    {
      "mikan_id": "1195",
      "bgmtv_id": 193562,
      "title_chinese": "Rewrite 第二季",
      "title_japanese": "Rewrite 2nd Season",
      "air_week": 6,
      "poster_url": "https://mikanani.me/images/Bangumi/201701/c31738eb.jpg",
      "year": 2017,
      "platform": "tv",
      "total_episodes": 11,
      "air_date": "2017-01-14"
    },
    {
      "mikan_id": "1226",
      "bgmtv_id": 191056,
      "title_chinese": "龙的牙医",
      "title_japanese": "龍の歯医者",
      "air_week": 6,
      "poster_url": "https://mikanani.me/images/Bangumi/201702/5cc2eca5.jpg",
      "year": 2017,
      "platform": "tv",
      "total_episodes": 2,
      "air_date": "2017-02-18"
    },
    {
      "mikan_id": "279",
      "bgmtv_id": 92161,
      "title_chinese": "游戏王ARC-V",
      "title_japanese": "遊☆戯☆王ARC-V",
      "air_week": 0,
      "poster_url": "https://mikanani.me/images/Bangumi/201404/a5d98c77.jpg",
      "year": 2014,
      "platform": "tv",
      "total_episodes": 148,
      "air_date": "2014-04-06"
    },
    {
      "mikan_id": "228",
      "bgmtv_id": 975,
      "title_chinese": "航海王",
      "title_japanese": "ONE PIECE",
      "air_week": 0,
      "poster_url": "https://mikanani.me/images/Bangumi/201310/0aa598c7.jpg",
      "year": 1999,
      "platform": "tv",
      "total_episodes": 1191,
      "air_date": "1999-10-20"
    },
    {
      "mikan_id": "227",
      "bgmtv_id": 899,
      "title_chinese": "名侦探柯南",
      "title_japanese": "名探偵コナン",
      "air_week": 0,
      "poster_url": "https://mikanani.me/images/Bangumi/201310/91d95f43.jpg",
      "year": 1996,
      "platform": "tv",
      "total_episodes": 1308,
      "air_date": "1996-01-08"
    },
    {
      "mikan_id": "828",
      "bgmtv_id": 146754,
      "title_chinese": "怪物猎人物语 RIDE ON",
      "title_japanese": "モンスターハンター ストーリーズ RIDE ON",
      "air_week": 0,
      "poster_url": "https://mikanani.me/images/Bangumi/201610/52af67c4.jpg",
      "year": 2016,
      "platform": "tv",
      "total_episodes": 75,
      "air_date": "2016-10-02"
    },
    {
      "mikan_id": "884",
      "bgmtv_id": 192680,
      "title_chinese": "精灵宝可梦 太阳&月亮",
      "title_japanese": "ポケットモンスター サン＆ムーン",
      "air_week": 0,
      "poster_url": "https://mikanani.me/images/Bangumi/201611/8193c704.jpg",
      "year": 2016,
      "platform": "tv",
      "total_episodes": 146,
      "air_date": "2016-11-17"
    },
    {
      "mikan_id": "1205",
      "bgmtv_id": 196773,
      "title_chinese": "Fate/Grand Order -First Order-",
      "title_japanese": "Fate/Grand Order -First Order-",
      "air_week": 6,
      "poster_url": "https://mikanani.me/images/Bangumi/201612/5e16e755.jpg",
      "year": 2016,
      "platform": "tv",
      "total_episodes": 1,
      "air_date": "2016-12-31"
    },
    {
      "mikan_id": "1171",
      "bgmtv_id": 185792,
      "title_chinese": "小魔女学园",
      "title_japanese": "リトルウィッチアカデミア",
      "air_week": 0,
      "poster_url": "https://mikanani.me/images/Bangumi/201701/6e0ba823.jpg",
      "year": 2017,
      "platform": "tv",
      "total_episodes": 25,
      "air_date": "2017-01-08"
    },
    {
      "mikan_id": "679",
      "bgmtv_id": 159826,
      "title_chinese": "魔法使光之美少女！",
      "title_japanese": "魔法つかいプリキュア!",
      "air_week": 0,
      "poster_url": "https://mikanani.me/images/Bangumi/201601/804a38ce.jpg",
      "year": 2016,
      "platform": "tv",
      "total_episodes": 50,
      "air_date": "2016-02-07"
    },
    {
      "mikan_id": "674",
      "bgmtv_id": 162663,
      "title_chinese": "莉露莉露妖精莉露～妖精之门～",
      "title_japanese": "リルリルフェアリル～妖精のドア～",
      "air_week": 6,
      "poster_url": "https://mikanani.me/images/Bangumi/201601/ff75c21a.jpg",
      "year": 2016,
      "platform": "tv",
      "total_episodes": 60,
      "air_date": "2016-02-06"
    },
    {
      "mikan_id": "836",
      "bgmtv_id": 189659,
      "title_chinese": "青鬼",
      "title_japanese": "あおおに ～じ・あにめぇしょん～",
      "air_week": 0,
      "poster_url": "https://mikanani.me/images/Bangumi/201610/ae1630f0.jpg",
      "year": 2016,
      "platform": "tv",
      "total_episodes": 13,
      "air_date": "2016-10-02"
    },
    {
      "mikan_id": "1223",
      "bgmtv_id": 196053,
      "title_chinese": "光之美少女 食尚甜心",
      "title_japanese": "キラキラ☆プリキュアアラモード",
      "air_week": 0,
      "poster_url": "https://mikanani.me/images/Bangumi/201702/88b3ba48.jpg",
      "year": 2017,
      "platform": "tv",
      "total_episodes": 49,
      "air_date": "2017-02-05"
    },
    {
      "mikan_id": "702",
      "bgmtv_id": 137693,
      "title_chinese": "霸旋陀螺 爆刃对决",
      "title_japanese": "ベイブレード バースト",
      "air_week": 1,
      "poster_url": "https://mikanani.me/images/Bangumi/201604/67f93012.jpg",
      "year": 2016,
      "platform": "tv",
      "total_episodes": 51,
      "air_date": "2016-04-04"
    },
    {
      "mikan_id": "1181",
      "bgmtv_id": 193282,
      "title_chinese": "猫咪日常",
      "title_japanese": "にゃんこデイズ",
      "air_week": 0,
      "poster_url": "https://mikanani.me/images/Bangumi/201701/4e653520.jpg",
      "year": 2017,
      "platform": "tv",
      "total_episodes": 12,
      "air_date": "2017-01-08"
    },
    {
      "mikan_id": "1180",
      "bgmtv_id": 171363,
      "title_chinese": "宇宙警探elDLIVE",
      "title_japanese": "エルドライブ【ēlDLIVE】",
      "air_week": 0,
      "poster_url": "https://mikanani.me/images/Bangumi/201701/eb0de534.jpg",
      "year": 2017,
      "platform": "tv",
      "total_episodes": 12,
      "air_date": "2017-01-08"
    },
    {
      "mikan_id": "830",
      "bgmtv_id": 170191,
      "title_chinese": "机动战士高达 铁血的奥尔芬斯 第二季",
      "title_japanese": "機動戦士ガンダム 鉄血のオルフェンズ 弐",
      "air_week": 0,
      "poster_url": "https://mikanani.me/images/Bangumi/201610/2fa12b94.jpg",
      "year": 2016,
      "platform": "tv",
      "total_episodes": 25,
      "air_date": "2016-10-02"
    },
    {
      "mikan_id": "1183",
      "bgmtv_id": 192485,
      "title_chinese": "偶像事变",
      "title_japanese": "アイドル事変",
      "air_week": 0,
      "poster_url": "https://mikanani.me/images/Bangumi/201701/a8ffbcbc.jpg",
      "year": 2017,
      "platform": "tv",
      "total_episodes": 12,
      "air_date": "2017-01-08"
    },
    {
      "mikan_id": "765",
      "bgmtv_id": 169076,
      "title_chinese": "智龙迷城X",
      "title_japanese": "パズドラクロス",
      "air_week": 1,
      "poster_url": "https://mikanani.me/images/Bangumi/201607/d214be85.jpg",
      "year": 2016,
      "platform": "tv",
      "total_episodes": 89,
      "air_date": "2016-07-04"
    },
    {
      "mikan_id": "1218",
      "bgmtv_id": 199827,
      "title_chinese": "暗芝居 第四季",
      "title_japanese": "闇芝居 第4期",
      "air_week": 0,
      "poster_url": "https://mikanani.me/images/Bangumi/201701/21a907a4.jpg",
      "year": 2017,
      "platform": "tv",
      "total_episodes": 13,
      "air_date": "2017-01-15"
    },
    {
      "mikan_id": "1207",
      "bgmtv_id": 187502,
      "title_chinese": "重力眩晕 序章",
      "title_japanese": "GRAVITY DAZE The Animation ～Ouverture～",
      "air_week": 0,
      "poster_url": "https://mikanani.me/images/Bangumi/201612/900eccf1.jpg",
      "year": 2016,
      "platform": "tv",
      "total_episodes": 1,
      "air_date": "2016-12-25"
    },
    {
      "mikan_id": "1163",
      "bgmtv_id": 148181,
      "title_chinese": "飙速宅男 新世代",
      "title_japanese": "弱虫ペダル NEW GENERATION",
      "air_week": 1,
      "poster_url": "https://mikanani.me/images/Bangumi/201701/3a6fc691.jpg",
      "year": 2017,
      "platform": "tv",
      "total_episodes": 25,
      "air_date": "2017-01-09"
    },
    {
      "mikan_id": "842",
      "bgmtv_id": 184153,
      "title_chinese": "TRICKSTER -来自江户川乱步「少年侦探团」-",
      "title_japanese": "TRICKSTER -江戸川乱歩「少年探偵団」より-",
      "air_week": 1,
      "poster_url": "https://mikanani.me/images/Bangumi/201610/6aab25aa.jpg",
      "year": 2016,
      "platform": "tv",
      "total_episodes": 25,
      "air_date": "2016-10-03"
    },
    {
      "mikan_id": "1159",
      "bgmtv_id": 188091,
      "title_chinese": "珈百璃的堕落",
      "title_japanese": "ガヴリールドロップアウト",
      "air_week": 1,
      "poster_url": "https://mikanani.me/images/Bangumi/201701/36799ce1.jpg",
      "year": 2017,
      "platform": "tv",
      "total_episodes": 14,
      "air_date": "2017-01-09"
    },
    {
      "mikan_id": "1165",
      "bgmtv_id": 191523,
      "title_chinese": "鬼平",
      "title_japanese": "鬼平",
      "air_week": 1,
      "poster_url": "https://mikanani.me/images/Bangumi/201701/32052e07.jpg",
      "year": 2017,
      "platform": "tv",
      "total_episodes": 13,
      "air_date": "2017-01-09"
    },
    {
      "mikan_id": "1170",
      "bgmtv_id": 194106,
      "title_chinese": "超·少年侦探团NEO",
      "title_japanese": "超・少年探偵団NEO",
      "air_week": 1,
      "poster_url": "https://mikanani.me/images/Bangumi/201701/e737da65.jpg",
      "year": 2017,
      "platform": "tv",
      "total_episodes": 13,
      "air_date": "2017-01-02"
    },
    {
      "mikan_id": "1185",
      "bgmtv_id": 195669,
      "title_chinese": "新撰组镇魂歌 二分之一",
      "title_japanese": "ちるらん にぶんの壱",
      "air_week": 1,
      "poster_url": "https://mikanani.me/images/Bangumi/201701/f81a19f7.jpg",
      "year": 2017,
      "platform": "tv",
      "total_episodes": 12,
      "air_date": "2017-01-09"
    },
    {
      "mikan_id": "709",
      "bgmtv_id": 162802,
      "title_chinese": "美妙天堂 第三期",
      "title_japanese": "プリパラ 3rd season",
      "air_week": 2,
      "poster_url": "https://mikanani.me/images/Bangumi/201604/31879e3e.jpg",
      "year": 2016,
      "platform": "tv",
      "total_episodes": 51,
      "air_date": "2016-04-05"
    },
    {
      "mikan_id": "815",
      "bgmtv_id": 190793,
      "title_chinese": "喵楞！",
      "title_japanese": "にゃんぼー！",
      "air_week": 2,
      "poster_url": "https://mikanani.me/images/Bangumi/201609/9f48649c.jpg",
      "year": 2016,
      "platform": "tv",
      "total_episodes": 26,
      "air_date": "2016-09-27"
    },
    {
      "mikan_id": "845",
      "bgmtv_id": 170242,
      "title_chinese": "信长的忍者",
      "title_japanese": "信長の忍び",
      "air_week": 2,
      "poster_url": "https://mikanani.me/images/Bangumi/201610/5870ed3b.jpg",
      "year": 2016,
      "platform": "tv",
      "total_episodes": 28,
      "air_date": "2016-10-04"
    },
    {
      "mikan_id": "1186",
      "bgmtv_id": 183492,
      "title_chinese": "ACCA13区监察课",
      "title_japanese": "ACCA13区監察課",
      "air_week": 2,
      "poster_url": "https://mikanani.me/images/Bangumi/201701/2ccb9e5c.jpg",
      "year": 2017,
      "platform": "tv",
      "total_episodes": 18,
      "air_date": "2017-01-10"
    },
    {
      "mikan_id": "1167",
      "bgmtv_id": 196188,
      "title_chinese": "漫研部～Surgical Friends～",
      "title_japanese": "あいまいみー～Surgical Friends～",
      "air_week": 2,
      "poster_url": "https://mikanani.me/images/Bangumi/201701/9fda270e.jpg",
      "year": 2017,
      "platform": "tv",
      "total_episodes": 13,
      "air_date": "2017-01-03"
    },
    {
      "mikan_id": "1188",
      "bgmtv_id": 176478,
      "title_chinese": "兽娘动物园",
      "title_japanese": "けものフレンズ",
      "air_week": 2,
      "poster_url": "https://mikanani.me/images/Bangumi/201701/6c73b6f5.jpg",
      "year": 2017,
      "platform": "tv",
      "total_episodes": 17,
      "air_date": "2017-01-10"
    },
    {
      "mikan_id": "1187",
      "bgmtv_id": 174592,
      "title_chinese": "Hand Shakers",
      "title_japanese": "ハンドシェイカー",
      "air_week": 2,
      "poster_url": "https://mikanani.me/images/Bangumi/201701/b30d6233.jpg",
      "year": 2017,
      "platform": "tv",
      "total_episodes": 13,
      "air_date": "2017-01-10"
    }
  ]
}